ModuleContextStreaming/__init__.py
ModuleContextStreaming/auth.py
ModuleContextStreaming/client.py
ModuleContextStreaming/exceptions.py
ModuleContextStreaming/mcs_mcp_adapter.py
ModuleContextStreaming/mcs_pb2.py
ModuleContextStreaming/mcs_pb2_grpc.py
ModuleContextStreaming/server.py
ModuleContextStreaming/servicer.py
modulecontextstreaming-0.0.7.dist-info/licenses/LICENSE.md
modulecontextstreaming-0.0.7.dist-info/METADATA
modulecontextstreaming-0.0.7.dist-info/WHEEL
modulecontextstreaming-0.0.7.dist-info/top_level.txt
modulecontextstreaming-0.0.7.dist-info/RECORD
