Metadata-Version: 2.4
Name: ModuleContextStreaming
Version: 0.0.7
Summary: A gRPC service for providing real-time, streamable context to LLMs.
Author-email: Sam Armstrong <sam@personalailabs.com>
License-Expression: MIT
Project-URL: Homepage, https://github.com/armstrongsam25/ModuleContextStreaming
Project-URL: Bug Tracker, https://github.com/armstrongsam25/ModuleContextStreaming/issues
Classifier: Programming Language :: Python :: 3
Classifier: Operating System :: OS Independent
Classifier: Development Status :: 3 - Alpha
Classifier: Intended Audience :: Developers
Classifier: Topic :: Scientific/Engineering :: Artificial Intelligence
Requires-Python: >=3.10
License-File: LICENSE.md
Requires-Dist: grpcio~=1.75.1
Requires-Dist: protobuf~=6.32.1
Requires-Dist: python-jose[cryptography]~=3.5.0
Requires-Dist: requests~=2.32.5
Requires-Dist: mcp~=1.15.0
Requires-Dist: openai~=2.1.0
Provides-Extra: dev
Requires-Dist: grpcio-tools~=1.75.1; extra == "dev"
Requires-Dist: pytest~=8.4.2; extra == "dev"
Requires-Dist: ruff~=0.13.2; extra == "dev"
Requires-Dist: python-dotenv~=1.1.1; extra == "dev"
Requires-Dist: cryptography~=46.0.1; extra == "dev"
Requires-Dist: mcp~=1.15.0; extra == "dev"
Requires-Dist: openai~=2.1.0; extra == "dev"
Dynamic: license-file
